[
  {
    "id": 51001,
    "名号": "墨蛟",
    "class": "怪物",
    "type": "小型",
    "攻击": 0.4,
    "防御": 0.4,
    "当前血量": 0.3,
    "暴击率": 0.1
  },
  {
    "id": 51001,
    "名号": "婴鲤兽",
    "class": "怪物",
    "type": "小型",
    "攻击": 0.4,
    "防御": 0.3,
    "当前血量": 0.3,
    "暴击率": 0.1
  },
  {
    "id": 50001,
    "名号": "鱼身尾",
    "class": "怪物",
    "type": "小型",
    "攻击": 0.3,
    "防御": 0.3,
    "当前血量": 0.4,
    "暴击率": 0.1
  },
  {
    "id": 50002,
    "名号": "千目妖",
    "class": "怪物",
    "type": "小型",
    "攻击": 0.3,
    "防御": 0.2,
    "当前血量": 0.4,
    "暴击率": 0.1
  },
  {
    "id": 50003,
    "名号": "鸡冠蛟",
    "class": "怪物",
    "type": "大型",
    "攻击": 0.4,
    "防御": 0.3,
    "当前血量": 0.5,
    "暴击率": 0.1
  },
  {
    "id": 50004,
    "名号": "妖冠蛇",
    "class": "怪物",
    "type": "大型",
    "攻击": 0.2,
    "防御": 0.3,
    "当前血量": 0.4,
    "暴击率": 0.2
  },
  {
    "id": 50005,
    "名号": "火鳞兽",
    "class": "怪物",
    "type": "大型",
    "攻击": 0.3,
    "防御": 0.3,
    "当前血量": 0.4,
    "暴击率": 0.2
  },
  {
    "id": 50007,
    "名号": "卧虎鲨",
    "class": "怪物",
    "type": "大型",
    "攻击": 0.3,
    "防御": 0.4,
    "当前血量": 0.4,
    "暴击率": 0.2
  },
  {
    "id": 50007,
    "名号": "盘黎蚓",
    "class": "怪物",
    "type": "大型",
    "攻击": 0.3,
    "防御": 0.4,
    "当前血量": 0.4,
    "暴击率": 0.2
  },
  {
    "id": 50008,
    "名号": "鹰鸢兽",
    "class": "怪物",
    "type": "大型",
    "攻击": 0.4,
    "防御": 0.5,
    "当前血量": 0.4,
    "暴击率": 0.4
  },
  {
    "id": 50009,
    "名号": "琉璃兽",
    "class": "怪物",
    "type": "魔神",
    "攻击": 0.5,
    "防御": 0.3,
    "当前血量": 0.4,
    "暴击率": 0.4
  },
  {
    "id": 50010,
    "名号": "银翼鸟",
    "class": "怪物",
    "type": "魔神",
    "攻击": 0.4,
    "防御": 0.3,
    "当前血量": 0.3,
    "暴击率": 0.3
  },
  {
    "id": 50011,
    "名号": "吞海鱼",
    "class": "怪物",
    "type": "魔神",
    "攻击": 0.5,
    "防御": 0.2,
    "当前血量": 0.6,
    "暴击率": 0.4
  },
  {
    "id": 50012,
    "名号": "紫云鹰",
    "class": "怪物",
    "type": "魔神",
    "攻击": 0.4,
    "防御": 0.3,
    "当前血量": 0.3,
    "暴击率": 0.4
  },
  {
    "id": 50012,
    "名号": "银光鼠",
    "class": "怪物",
    "type": "魔神",
    "攻击": 0.4,
    "防御": 0.3,
    "当前血量": 0.5,
    "暴击率": 0.3
  },
  {
    "id": 50006,
    "名号": "韩立",
    "class": "怪物",
    "type": "真仙",
    "攻击": 0.6,
    "防御": 0.5,
    "当前血量": 0.4,
    "暴击率": 0.3
  }
]
