[
  {
    "id": 40000001,
    "name": "昆仑山",
    "efficiency": 1,
    "level": 5
  },
  {
    "id": 30000001,
    "name": "三清山",
    "efficiency": 0.7,
    "level": 4
  },
  {
    "id": 30000002,
    "name": "斩神涯",
    "efficiency": 0.7,
    "level": 4
  },
  {
    "id": 30000003,
    "name": "封魔谷",
    "efficiency": 0.7,
    "level": 4
  },
  {
    "id": 30000004,
    "name": "星阁",
    "efficiency": 0.7,
    "level": 4
  },
  {
    "id": 30000005,
    "name": "老君山",
    "efficiency": 0.7,
    "level": 4
  },
  {
    "id": 2000001,
    "name": "天山",
    "efficiency": 0.5,
    "level": 3
  },
  {
    "id": 2000002,
    "name": "青城山",
    "efficiency": 0.5,
    "level": 3
  },
  {
    "id": 2000003,
    "name": "天目山",
    "efficiency": 0.5,
    "level": 3
  },
  {
    "id": 2000004,
    "name": "武当山",
    "efficiency": 0.5,
    "level": 3
  },
  {
    "id": 2000005,
    "name": "灵台山",
    "efficiency": 0.5,
    "level": 3
  },
  {
    "id": 2000006,
    "name": "泰山",
    "efficiency": 0.5,
    "level": 3
  },
  {
    "id": 1000001,
    "name": "罗浮山",
    "efficiency": 0.3,
    "level": 2
  },
  {
    "id": 1000002,
    "name": "方寸山",
    "efficiency": 0.3,
    "level": 2
  },
  {
    "id": 1000003,
    "name": "琥牢山",
    "efficiency": 0.3,
    "level": 2
  }
]
