[
    {
        "id": 1,
        "name": "无欲天仙",
        "Grade": "限定*仙府",
        "Best": [
            "[黎明剑][逆天甲][天书][一梦成仙]"
        ],
        "Price": 700000,
        "experience": 300000,
        "one": [
            {
                "id": 4232,
                "name": "道丹",
                "class": "4",
                "type": "2",
                "exp": 500000,
                "acount": 1,
                "price": 300000
            },
            {
                "id": 5128,
                "name": "太玄经",
                "class": "5",
                "type": "1",
                "size": 0.35,
                "acount": 1,
                "price": 350000
            },
            {
                "id": 5129,
                "name": "太乙经",
                "class": "5",
                "type": "1",
                "size": 0.35,
                "acount": 1,
                "price": 350000
            },
            {
                "id": 5130,
                "name": "太白经",
                "class": "5",
                "type": "1",
                "size": 0.35,
                "acount": 1,
                "price": 350000
            }
        ],
        "two": [
        {
            "id": 3118,
            "name": "破天莲",
            "class": "3",
            "type": "1",
            "atk": 300000,
            "def": 20000,
            "HP": 20000,
            "bao": 0.3,
            "speed": 0,
            "atkpercentage": 0,
            "defpercentage": 0,
            "HPpercentage": 0,
            "acount": 1,
            "price": 450000
        },
        {
            "id": 2116,
            "name": "龙鳞",
            "class": "2",
            "type": "1",
            "atk": 20000,
            "def": 300000,
            "HP": 20000,
            "bao": 0.15,
            "speed": 0,
            "atkpercentage": 0,
            "defpercentage": 0,
            "HPpercentage": 0,
            "acount": 1,
            "price": 450000
        },
        {
            "id": 1119,
            "name": "饮血剑",
            "class": "1",
            "type": "1",
            "atk": 300000,
            "def": 20000,
            "HP": 20000,
            "bao": 0.15,
            "speed": 0,
            "atkpercentage": 0,
            "defpercentage": 0,
            "HPpercentage": 0,
            "acount": 1,
            "price": 450000
        }
        ],
        "three": [
            {
                "id": 131101,
                "name": "黎明剑",
                "class": "1",
                "type": "1",
                "atk": 500000,
                "def": 200,
                "HP": 200,
                "bao": 0.1,
                "speed": 0,
                "atkpercentage": 0,
                "defpercentage": 0,
                "HPpercentage": 0,
                "acount": 1,
                "price": 1
            },
            {
                "id": 132101,
                "name": "逆天甲",
                "class": "2",
                "type": "1",
                "atk": 100000,
                "def": 400000,
                "HP": 200,
                "bao": 0.2,
                "speed": 0,
                "atkpercentage": 0,
                "defpercentage": 0,
                "HPpercentage": 0,
                "acount": 1,
                "price": 1
            },
            {
                "id": 135101,
                "name": "天书",
                "class": "5",
                "type": "1",
                "size": 1.0,
                "acount": 1,
                "price": 1
            },
            {
                "id": 134002,
                "name": "一梦成仙",
                "class": "4",
                "type": "2",
                "exp": 2000000,
                "acount": 1,
                "price": 1
            }
        ]
    }
]