[
    {
        "id": "5-1-20",
        "name": "红楼梦",
        "attack": 1,
        "defense": 1,
        "blood": 1,
        "burst": 1,
        "burstmax": 1,
        "size": 100,
        "experience": 1,
        "experiencemax": 1,
        "speed": 1,
        "acount": 1,
        "price": 88000
    },
    {
        "id": "5-1-21",
        "name": "西游记",
        "attack": 1,
        "defense": 1,
        "blood": 1,
        "burst": 1,
        "burstmax": 1,
        "size": 105,
        "experience": 1,
        "experiencemax": 1,
        "speed": 1,
        "acount": 1,
        "price": 140000
    },
    {
        "id": "5-1-22",
        "name": "三国演义",
        "attack": 1,
        "defense": 1,
        "blood": 1,
        "burst": 1,
        "burstmax": 1,
        "size": 110,
        "experience": 1,
        "experiencemax": 1,
        "speed": 1,
        "acount": 1,
        "price": 200000
    },
    {
        "id": "5-1-23",
        "name": "水浒传",
        "attack": 1,
        "defense": 1,
        "blood": 1,
        "burst": 1,
        "burstmax": 1,
        "size": 115,
        "experience": 1,
        "experiencemax": 1,
        "speed": 1,
        "acount": 1,
        "price": 300000
    },
    {
        "id": "5-1-24",
        "name": "金瓶梅",
        "attack": 1,
        "defense": 1,
        "blood": 1,
        "burst": 1,
        "burstmax": 1,
        "size": 120,
        "experience": 1,
        "experiencemax": 1,
        "speed": 1,
        "acount": 1,
        "price": 450000
    },
    {
        "id": "5-1-25",
        "name": "我佛慈悲",
        "attack": 1,
        "defense": 1,
        "blood": 1,
        "burst": 1,
        "burstmax": 1,
        "size": 125,
        "experience": 1,
        "experiencemax": 1,
        "speed": 1,
        "acount": 1,
        "price": 670000
    },
    {
        "id": "5-1-26",
        "name": "立地成佛",
        "attack": 1,
        "defense": 1,
        "blood": 1,
        "burst": 1,
        "burstmax": 1,
        "size": 130,
        "experience": 1,
        "experiencemax": 1,
        "speed": 1,
        "acount": 1,
        "price": 100000
    },
    {
        "id": "5-1-27",
        "name": "太玄经",
        "attack": 1,
        "defense": 1,
        "blood": 1,
        "burst": 1,
        "burstmax": 1,
        "size": 135,
        "experience": 1,
        "experiencemax": 1,
        "speed": 1,
        "acount": 1,
        "price": 1500000
    },
    {
        "id": "5-1-28",
        "name": "太乙经",
        "attack": 1,
        "defense": 1,
        "blood": 1,
        "burst": 1,
        "burstmax": 1,
        "size": 140,
        "experience": 1,
        "experiencemax": 1,
        "speed": 1,
        "acount": 1,
        "price": 2300000
    },
    {
        "id": "5-1-29",
        "name": "太白经",
        "attack": 1,
        "defense": 1,
        "blood": 1,
        "burst": 1,
        "burstmax": 1,
        "size": 145,
        "experience": 1,
        "experiencemax": 1,
        "speed": 1,
        "acount": 1,
        "price": 3400000
    },
    {
        "id": "5-1-30",
        "name": "天书",
        "attack": 1,
        "defense": 1,
        "blood": 1,
        "burst": 1,
        "burstmax": 1,
        "size": 150,
        "experience": 1,
        "experiencemax": 1,
        "speed": 1,
        "acount": 1,
        "price": 5100000
    },
    {
        "id": "5-1-31",
        "name": "一指天道",
        "attack": 1,
        "defense": 1,
        "blood": 1,
        "burst": 1,
        "burstmax": 1,
        "size": 155,
        "experience": 1,
        "experiencemax": 1,
        "speed": 1,
        "acount": 1,
        "price": 7600000
    }
]